SBILib/__init__.py
SBILib/beans/Executable.py
SBILib/beans/File.py
SBILib/beans/IndexedNum.py
SBILib/beans/JSONer.py
SBILib/beans/Path.py
SBILib/beans/StorableObject.py
SBILib/beans/__init__.py
SBILib/beans/butler.py
SBILib/beans/singleton.py
SBILib/data/Alphabet.py
SBILib/data/AminoAcids.py
SBILib/data/AtomVariants.py
SBILib/data/Element.py
SBILib/data/Properties.py
SBILib/data/SetDict.py
SBILib/data/__init__.py
SBILib/databases/AlphaFoldlink.py
SBILib/databases/CATHlink.py
SBILib/databases/DrugBanklink.py
SBILib/databases/Enzymelink.py
SBILib/databases/GOlink.py
SBILib/databases/PDBTMlink.py
SBILib/databases/PDBeChemConnect.py
SBILib/databases/PDBeChemlink.py
SBILib/databases/PDBlink.py
SBILib/databases/SCOPlink.py
SBILib/databases/TaxIDlink.py
SBILib/databases/Uniprotlink.py
SBILib/databases/__Uniprotlink.py
SBILib/databases/__init__.py
SBILib/databases/dblink.py
SBILib/databases/uniprot/__init__.py
SBILib/databases/uniprot/connect.py
SBILib/databases/uniprot/uniprot.py
SBILib/error/BlastError.py
SBILib/error/FileError.py
SBILib/error/SeqAliError.py
SBILib/error/__init__.py
SBILib/external/README.md
SBILib/external/__init__.py
SBILib/external/configSBI.txt
SBILib/external/CDhit/CDhit.py
SBILib/external/CDhit/CDhitExe.py
SBILib/external/CDhit/CDhitHomolog.py
SBILib/external/CDhit/CDhitList.py
SBILib/external/CDhit/__init__.py
SBILib/external/DSSP/DSSP.py
SBILib/external/DSSP/DSSPExe.py
SBILib/external/DSSP/__init__.py
SBILib/external/blast/BlastExe.py
SBILib/external/blast/BlastHit.py
SBILib/external/blast/BlastResult.py
SBILib/external/blast/__init__.py
SBILib/external/blast/blast_parser.py
SBILib/math/__init__.py
SBILib/math/stats.py
SBILib/sequence/Fasta.py
SBILib/sequence/IndexedSeqAli.py
SBILib/sequence/SeqAli.py
SBILib/sequence/Sequence.py
SBILib/sequence/__init__.py
SBILib/sequence/alignment/Needleman_Wunsch.py
SBILib/sequence/alignment/SeqAli.py
SBILib/sequence/alignment/SimilarityMatrix.py
SBILib/sequence/alignment/__init__.py
SBILib/structure/PDB.py
SBILib-0.3.12.dist-info/METADATA
SBILib-0.3.12.dist-info/WHEEL
SBILib-0.3.12.dist-info/top_level.txt
SBILib-0.3.12.dist-info/RECORD
