Metadata-Version: 2.1
Name: SBILib
Version: 0.3.12
Summary: UNKNOWN
Home-page: https://github.com/structuralbioinformatics/SBI
Author: Patrick Gohl
Author-email: patrick.gohl@upf.edu
License: MIT
Keywords: Structural Bioinformatics,Loops
Platform: UNKNOWN
Requires-Dist: numpy
Requires-Dist: pandas
Requires-Dist: pynion
Requires-Dist: Requests
Requires-Dist: scipy
Requires-Dist: six
